setup.py
betterast/__init__.py
betterast/ast.py
betterast.egg-info/PKG-INFO
betterast.egg-info/SOURCES.txt
betterast.egg-info/dependency_links.txt
betterast.egg-info/not-zip-safe
betterast.egg-info/top_level.txt
bin/treedot