Metadata-Version: 1.1
Name: betterast
Version: 0.4
Summary: A generic ast.
Home-page: https://github.com/timtadh/betterast
Author: Tim Henderson
Author-email: tadh@case.edu
License: UNKNOWN
Platform: unix
Provides: betterast
